Metadata-Version: 2.4
Name: mcp-server-deepsearch
Version: 0.1.0
Summary: 实现类deepresearch功能的MCP工具
Requires-Python: >=3.11
Requires-Dist: asyncio>=3.4.3
Requires-Dist: mcp>=1.6.0
Requires-Dist: openai>=1.76.0
Requires-Dist: openai-agents>=0.0.13
Requires-Dist: pydantic>=2.11.3
Requires-Dist: typing>=3.10.0.0
